akfraction
